boursobank/__init__.py
boursobank/__main__.py
boursobank/py.typed
boursobank/statements.py
boursobank-0.5.dist-info/entry_points.txt
boursobank-0.5.dist-info/LICENSE
boursobank-0.5.dist-info/WHEEL
boursobank-0.5.dist-info/METADATA
boursobank-0.5.dist-info/RECORD
